controlSBML/__init__.py
controlSBML/_version.py
controlSBML/antimony_builder.py
controlSBML/constants.py
controlSBML/control_sbml.py
controlSBML/dict_array.py
controlSBML/gpz_fitter.py
controlSBML/grid.py
controlSBML/iterate_biomodels.py
controlSBML/make_roadrunner.py
controlSBML/msgs.py
controlSBML/option_set.py
controlSBML/parallel_coordinates.py
controlSBML/parallel_search.py
controlSBML/point_evaluator.py
controlSBML/poly_fitter.py
controlSBML/sbml_system.py
controlSBML/siso_closed_loop_designer.py
controlSBML/siso_maker.py
controlSBML/siso_transfer_function_builder.py
controlSBML/siso_transfer_function_fitter.py
controlSBML/staircase.py
controlSBML/timeseries.py
controlSBML/util.py
controlSBML/archive/__init__.py
controlSBML/archive/control_analysis.py
controlSBML/archive/control_base.py
controlSBML/archive/control_plot.py
controlSBML/archive/control_sbml.py
controlSBML/archive/history.py
controlSBML/archive/iosystem_factory.py
controlSBML/archive/logger.py
controlSBML/archive/mimo_transfer_function_builder.py
controlSBML/archive/nonlinear_io_system.py
controlSBML/archive/sequential_model.py
controlSBML/archive/simulate_system.py
controlSBML/archive/siso_closed_loop_designer.py
controlSBML/archive/siso_closed_loop_system.py
controlSBML/archive/siso_design_evaluator.py
controlSBML/archive/siso_transfer_function_builder.py
controlSBML/archive/temporal_series.py
controlSBML/control_extensions/__init__.py
controlSBML/control_extensions/state_space_tf.py
controlSBML/option_management/__init__.py
controlSBML/option_management/option_manager.py
controlSBML/option_management/options.py
controlSBML-1.2.3.dist-info/LICENSE
controlSBML-1.2.3.dist-info/METADATA
controlSBML-1.2.3.dist-info/WHEEL
controlSBML-1.2.3.dist-info/top_level.txt
controlSBML-1.2.3.dist-info/RECORD
