Metadata-Version: 2.2
Name: controlSBML
Version: 1.2.3
Summary: Control analysis of SBML models
Author-email: Joseph Hellerstein <joseph.hellerstein@gmail.com>
License: MIT License
Project-URL: Homepage, https://github.com/ModelEngineering/controlSBML
Requires-Python: >=3.6
License-File: LICENSE
Requires-Dist: coverage
Requires-Dist: control
Requires-Dist: docstring-expander
Requires-Dist: jupyterlab
Requires-Dist: lmfit
Requires-Dist: matplotlib
Requires-Dist: numpy
Requires-Dist: pandas
Requires-Dist: pip
Requires-Dist: pylint
Requires-Dist: python-libsbml
Requires-Dist: seaborn
Requires-Dist: symmathSBML
Requires-Dist: sympy
Requires-Dist: tellurium
Requires-Dist: toml
Requires-Dist: tqdm
Requires-Dist: twine
Requires-Dist: urllib3
